base64io/__init__.py
base64io-1.0.2.data/data/CHANGELOG.rst
base64io-1.0.2.data/data/LICENSE
base64io-1.0.2.data/data/README.rst
base64io-1.0.2.dist-info/LICENSE.txt
base64io-1.0.2.dist-info/METADATA
base64io-1.0.2.dist-info/RECORD
base64io-1.0.2.dist-info/WHEEL
base64io-1.0.2.dist-info/top_level.txt
